alembic/__init__.py
alembic/autogenerate.bak.py
alembic/coloredlog.py
alembic/command.py
alembic/compat.py
alembic/config.py
alembic/context.py
alembic/environment.py
alembic/migration.py
alembic/op.py
alembic/operations.py
alembic/script.py
alembic/util.py
alembic/autogenerate/__init__.py
alembic/autogenerate/api.py
alembic/autogenerate/compare.py
alembic/autogenerate/render.py
alembic/ddl/__init__.py
alembic/ddl/base.py
alembic/ddl/impl.py
alembic/ddl/mssql.py
alembic/ddl/mysql.py
alembic/ddl/oracle.py
alembic/ddl/postgresql.py
alembic/ddl/sqlite.py
alembic/templates/generic/README
alembic/templates/generic/alembic.ini.mako
alembic/templates/generic/env.py
alembic/templates/generic/script.py.mako
alembic/templates/multidb/README
alembic/templates/multidb/alembic.ini.mako
alembic/templates/multidb/env.py
alembic/templates/multidb/script.py.mako
alembic/templates/pylons/README
alembic/templates/pylons/alembic.ini.mako
alembic/templates/pylons/env.py
alembic/templates/pylons/script.py.mako
uliweb_alembic-0.6.9.dist-info/DESCRIPTION.rst
uliweb_alembic-0.6.9.dist-info/METADATA
uliweb_alembic-0.6.9.dist-info/RECORD
uliweb_alembic-0.6.9.dist-info/WHEEL
uliweb_alembic-0.6.9.dist-info/entry_points.txt
uliweb_alembic-0.6.9.dist-info/metadata.json
uliweb_alembic-0.6.9.dist-info/top_level.txt
