Metadata-Version: 1.1
Name: uliweb-alembic
Version: 0.6.9
Summary: A port of alembic for uliweb framework.
Home-page: https://github.com/limodou/uliweb-alembic
Author: limodou
Author-email: limodou@gmail.com
License: MIT
Keywords: SQLAlchemy migrations
Platform: UNKNOWN
Classifier: Development Status :: 4 - Beta
Classifier: Environment :: Console
Classifier: Intended Audience :: Developers
Classifier: Programming Language :: Python
Classifier: Programming Language :: Python :: 3
Classifier: Programming Language :: Python :: Implementation :: CPython
Classifier: Programming Language :: Python :: Implementation :: PyPy
Classifier: Topic :: Database :: Front-Ends
